simplegraphicslibrary/__init__.py
simplegraphicslibrary/main.py
simplegraphicslibrary-0.0.1.dist-info/LICENSE
simplegraphicslibrary-0.0.1.dist-info/METADATA
simplegraphicslibrary-0.0.1.dist-info/WHEEL
simplegraphicslibrary-0.0.1.dist-info/top_level.txt
simplegraphicslibrary-0.0.1.dist-info/RECORD
